aioeapi/__init__.py
aioeapi/aio_portcheck.py
aioeapi/config_session.py
aioeapi/device.py
aioeapi/errors.py
aio_eapi-0.6.3.dist-info/LICENSE
aio_eapi-0.6.3.dist-info/METADATA
aio_eapi-0.6.3.dist-info/WHEEL
aio_eapi-0.6.3.dist-info/RECORD
