Metadata-Version: 2.1
Name: aio-eapi
Version: 0.6.3
Summary: Arista EOS API asyncio client
Author: Jeremy Schulman
Requires-Python: >=3.8
Classifier: Programming Language :: Python :: 3
Classifier: Programming Language :: Python :: 3.8
Classifier: Programming Language :: Python :: 3.9
Classifier: Programming Language :: Python :: 3.10
Classifier: Programming Language :: Python :: 3.11
Requires-Dist: httpx (>=0.23.3,<0.24.0)
